filecannon/__init__.py
filecannon/ai_manager.py
filecannon/file_manager.py
filecannon/filecannon.py
filecannon-0.1.6.dist-info/LICENSE
filecannon-0.1.6.dist-info/METADATA
filecannon-0.1.6.dist-info/WHEEL
filecannon-0.1.6.dist-info/entry_points.txt
filecannon-0.1.6.dist-info/top_level.txt
filecannon-0.1.6.dist-info/RECORD
