Metadata-Version: 2.2
Name: filecannon
Version: 0.1.6
Summary: AI-powered file generation CLI tool
Home-page: https://github.com/255BITS/filecannon
Author: 255BITS
Author-email: info@255labs.xyz
Classifier: Programming Language :: Python :: 3
Classifier: License :: OSI Approved :: MIT License
Classifier: Operating System :: OS Independent
Requires-Python: >=3.7
License-File: LICENSE
Requires-Dist: openai>=1.0.0
Requires-Dist: anthropic>=0.6.0
Dynamic: author
Dynamic: author-email
Dynamic: classifier
Dynamic: description
Dynamic: description-content-type
Dynamic: home-page
Dynamic: requires-dist
Dynamic: requires-python
Dynamic: summary
